innocuous_sdk/__init__.py
innocuous_sdk/sdk.py
innocuous_sdk-1.1.2.dist-info/METADATA
innocuous_sdk-1.1.2.dist-info/WHEEL
innocuous_sdk-1.1.2.dist-info/top_level.txt
innocuous_sdk-1.1.2.dist-info/RECORD
