Metadata-Version: 2.1
Name: innocuous-sdk
Version: 1.1.2
Summary: Innocuous Book SDK
Home-page: 
Author: Noam Rosenberg
Author-email: noamsrosenberg@gmail.com
License: UNKNOWN
Keywords: innocuousbook
Platform: UNKNOWN
Requires-Dist: innocuous-api (>=1.1.3)
